tsdb_wrapper/__init__.py
tsdb_wrapper/_meta.py
tsdb_wrapper/base.py
tsdb_wrapper/impl/__init__.py
tsdb_wrapper/impl/influx.py
tsdb_wrapper-0.0.0.dist-info/LICENSE.txt
tsdb_wrapper-0.0.0.dist-info/METADATA
tsdb_wrapper-0.0.0.dist-info/WHEEL
tsdb_wrapper-0.0.0.dist-info/top_level.txt
tsdb_wrapper-0.0.0.dist-info/RECORD
